pinyin_order/__init__.py
pinyin_order-0.0.1.dist-info/METADATA
pinyin_order-0.0.1.dist-info/WHEEL
pinyin_order-0.0.1.dist-info/licenses/LICENSE
pinyin_order-0.0.1.dist-info/RECORD
