Metadata-Version: 2.3
Name: pinyin-order
Version: 0.0.1
Summary: 包含中文的字符串使用拼音比较大小，可用于使用拼音排序字符串等的需求。
Project-URL: Homepage, https://github.com/Ryaningli/pinyin-order.git
Project-URL: Issues, https://github.com/Ryaningli/pinyin-order/issues
Author-email: Ryan Lee <ryaningli@foxmail.com>
License-File: LICENSE
Classifier: License :: OSI Approved :: MIT License
Classifier: Operating System :: OS Independent
Classifier: Programming Language :: Python :: 3
Requires-Python: >=3.8
Requires-Dist: pypinyin>=0.45.0
